LICENSE
MANIFEST.in
README.rst
setup.py
psas_packet/__init__.py
psas_packet/io.py
psas_packet/messages.py
psas_packet.egg-info/PKG-INFO
psas_packet.egg-info/SOURCES.txt
psas_packet.egg-info/dependency_links.txt
psas_packet.egg-info/not-zip-safe
psas_packet.egg-info/top_level.txt
scripts/autodoc
scripts/gen-psas-types
scripts/log2csv
scripts/replaylog
scripts/slicelog