Metadata-Version: 1.1
Name: psas-packet
Version: 0.2.2
Summary: serializer for PSAS data standards
Home-page: http://psas-packet-serializer.readthedocs.org
Author: Nathan Bergey
Author-email: nathan.bergey@gmail.com
License: GNU GENERAL PUBLIC LICENSE
